Metadata-Version: 2.1
Name: bbc-reader
Version: 1.0.3
Summary: Read the latest BBC news
Home-page: UNKNOWN
Author: Khang Nguyen
Author-email: khangvu.1109@gmail.com
License: MIT
Platform: UNKNOWN
Classifier: License :: OSI Approved :: MIT License
Classifier: Programming Language :: Python :: 3
Classifier: Programming Language :: Python :: 3.7
